reqman/__init__.py
reqman/__main__.py
reqman/com.py
reqman/common.py
reqman/env.py
reqman/testing.py
reqman/xlib.py
reqman-3.5.3.dist-info/WHEEL
reqman-3.5.3.dist-info/entry_points.txt
reqman-3.5.3.dist-info/METADATA
reqman-3.5.3.dist-info/RECORD
