Metadata-Version: 2.3
Name: reqman
Version: 3.5.3
Summary: Create your http(s)-tests in simple yaml files, and run them with command line, against various environments
Author: manatlan
Author-email: manatlan <manatlan@gmail.com>
License:                     GNU GENERAL PUBLIC LICENSE
Requires-Dist: httpx
Requires-Dist: httpx-socks
Requires-Dist: python-dotenv
Requires-Dist: py-dom-xpath-six
Requires-Dist: pyyaml>=4.2b1
Requires-Dist: stpl>=1.13.2
Requires-Dist: colorama
Requires-Dist: pyjwt
Requires-Dist: junit-xml
Requires-Python: >=3.9
Project-URL: Homepage, https://github.com/manatlan/reqman
Project-URL: Issues, https://github.com/manatlan/reqman/issues
Project-URL: Repository, https://github.com/manatlan/reqman
